{"current":{"color_primary":"#42b1ff","color_secondary":"#c985e5","color_tertiary":"#FF8B58","color_quaternary":"#3c2744","color_white":"#FFFFFF","color_black":"#191919","color_success":"#44b574","color_warning":"#f79009","color_error":"#e65561","color_info":"#42b1ff","color_neutral":"#f5f3ef","color_neutral_light":"#f5e5f9","color_neutral_dark":"#374151","space_xs":0.25,"space_sm":0.5,"space_md":1,"space_lg":1.5,"space_xl":2,"space_2xl":3,"space_3xl":4,"space_4xl":5,"space_5xl":6,"color_gray":"#f2f2f2","color_body":"#000000","font_family_primary":"NeueHaasDisplay, Arial, sans-serif","font_family_body":"Arial, sans-serif","font_family_handwritten":"FLFont, Arial, sans-serif","font_family_serif":"Georgia, serif","font_size_xs":0.75,"font_size_sm":0.875,"font_size_base":1,"font_size_lg":1.125,"font_size_xl":1.25,"font_size_2xl":1.5,"font_size_3xl":2,"font_size_4xl":2.5,"font_size_5xl":3,"font_size_6xl":4,"font_weight_light":300,"font_weight_regular":400,"font_weight_medium":500,"font_weight_bold":700,"font_weight_black":900,"line_height_none":1,"line_height_tight":1.125,"line_height_normal":1.2,"line_height_relaxed":1.42857143,"line_height_loose":1.625,"radius_none":0,"radius_sm":0.125,"radius_md":0.25,"radius_lg":0.5,"radius_xl":0.75,"radius_2xl":1,"radius_3xl":1.5,"button_border_radius":"rounded","space_1":0.25,"space_2":0.5,"space_3":0.75,"space_4":1,"space_5":1.25,"space_6":1.5,"space_8":2,"space_10":2.5,"space_12":3,"space_16":4,"space_20":5,"space_24":6,"heading_h1_size":2.375,"heading_h2_size":2,"heading_h3_size":1.5,"heading_h4_size":1.125,"heading_h5_size":0.875,"heading_h6_size":0.75}}